{"funcs_base_getrandomcolor.md":"DmHK4xmZ","index.md":"oJXSnC96","funcs_date_dayofyear.md":"Cys9YEjS","funcs_string_stringsize.md":"DkERtDeQ","funcs_string_getrandomstring.md":"Re4EbaUp","funcs_string_hasunicode.md":"DBCOP8sp","funcs_object_deepclone.md":"DQB--KWT","funcs_object_haskey.md":"DIgtjU3E","funcs_date_isdatelike.md":"GCiblDdn","funcs_object_isemptyobj.md":"qULZ49pl","funcs_date_isdate.md":"Db52kmz7","getting-started.md":"CX1m03Ok","funcs_object_isplainobject.md":"FWtnghrX","funcs_string_unicodesize.md":"Dom5du-b","funcs_base_copytxt.md":"CG7HDjWL","funcs_string_isstring.md":"GF80awr3","funcs_base_debounce.md":"BgtNxuAk"}
